ngcsimlib/__init__.py
ngcsimlib/_src/__init__.py
ngcsimlib/_src/component.py
ngcsimlib/_src/configManager.py
ngcsimlib/_src/deprecators.py
ngcsimlib/_src/logger.py
ngcsimlib/_src/compartment/__init__.py
ngcsimlib/_src/compartment/compartment.py
ngcsimlib/_src/compartment/compartmentMeta.py
ngcsimlib/_src/context/__init__.py
ngcsimlib/_src/context/context.py
ngcsimlib/_src/context/contextAwareObject.py
ngcsimlib/_src/context/contextAwareObjectMeta.py
ngcsimlib/_src/context/contextObjectDecorators.py
ngcsimlib/_src/context/context_manager.py
ngcsimlib/_src/global_state/__init__.py
ngcsimlib/_src/global_state/manager.py
ngcsimlib/_src/modules/__init__.py
ngcsimlib/_src/modules/modules_manager.py
ngcsimlib/_src/operations/BaseOp.py
ngcsimlib/_src/operations/Product.py
ngcsimlib/_src/operations/Summation.py
ngcsimlib/_src/operations/__init__.py
ngcsimlib/_src/parser/__init__.py
ngcsimlib/_src/parser/contextTransformer.py
ngcsimlib/_src/parser/kwargsTransformer.py
ngcsimlib/_src/parser/utils.py
ngcsimlib/_src/process/__init__.py
ngcsimlib/_src/process/baseProcess.py
ngcsimlib/_src/process/jointProcess.py
ngcsimlib/_src/process/methodProcess.py
ngcsimlib/_src/utils/__init__.py
ngcsimlib/_src/utils/help.py
ngcsimlib/_src/utils/io.py
ngcsimlib/_src/utils/modules.py
ngcsimlib/_src/utils/priority.py
ngcsimlib/compartment/__init__.py
ngcsimlib/context/__init__.py
ngcsimlib/global_state/__init__.py
ngcsimlib/logger/__init__.py
ngcsimlib/operations/__init__.py
ngcsimlib/parser/__init__.py
ngcsimlib-3.0.0.dist-info/licenses/AUTHORS
ngcsimlib-3.0.0.dist-info/licenses/LICENSE
ngcsimlib-3.0.0.dist-info/METADATA
ngcsimlib-3.0.0.dist-info/WHEEL
ngcsimlib-3.0.0.dist-info/top_level.txt
ngcsimlib-3.0.0.dist-info/RECORD
