Metadata-Version: 2.4
Name: ngcsimlib
Version: 3.0.0
Summary: Simulation software backend for ngc-learn.
Author-email: William Gebhardt <wdg1351@rit.edu>, Alexander Ororbia <ago@cs.rit.edu>
License: BSD-3-Clause License
Project-URL: Homepage, https://github.com/NACLab/ngc-sim-lib
Project-URL: Lab Page, https://www.cs.rit.edu/~ago/nac_lab.html
Keywords: python,complex-systems,simulation
Requires-Python: >=3.10
License-File: LICENSE
License-File: AUTHORS
Dynamic: license-file
